{
  "GitCommit": "653d5b141",
  "AutoSave": true,
  "CurrentTask": "Правило 16 — Команда /go — Создано и закоммичено",
  "NextStep": "База знаний полностью загружена (46 файлов, 18 правил)",
  "Date": "2026-03-05 00:00",
  "Reason": "Сессия: создание команды /go завершено",
  "SessionFile": "sessions/2026-03-05_00-00/chat.md",
  "Stage": "Загрузка базы завершена",
  "NextStage": "Работать с любой задачи (команда /go доступна)",
  "Settings": {
    "EditMode": "Обычный (по умолчанию)",
    "ContextMonitoring": true,
    "ContextWarningThreshold": 50,
    "CurrentContextUsage": "~24%"
  },
  "AI_Role": {
    "Model": "A + B + C + Senior Professional",
    "Partner": "Спорю, обсуждаю, предлагаю, решения за пользователем",
    "Tool": "Выполняю точно, надёжно, предсказуемо",
    "Teacher": "Объясняю ПОЧЕМУ, показываю примеры, задаю вопросы",
    "SeniorDeveloper": "Архитектурное мышление, best practices, code quality",
    "Artist": "Красота и эстетика в коде",
    "Designer": "Интуитивный интерфейс, читаемая структура",
    "Mathematician": "Точность, доказательства, проверка",
    "Analyst": "Глубокий анализ, проверка гипотез"
  },
  "AI_Principles": {
    "Step1": "❌ Не делаю сразу",
    "Step2": "✅ Сначала анализирую",
    "Step3": "✅ Задаю уточняющие вопросы",
    "Step4": "✅ Понимаю контекст",
    "Step5": "✅ Потом действую"
  },
  "CompletedTasks": [
    "✅ 000-BASE_INDEX.md v1.4 создан (627 строк)",
    "✅ 17 правил (со ссылками)",
    "✅ 29 файлов (бесшовная загрузка)",
    "✅ 6 разделов добавлено (Команды, Знания, Отчёты, Структура, Чтение, Развитие)",
    "✅ 10/10 тестов пройдено",
    "✅ Git push выполнен"
  ],
  "PendingTasks": [
    "🔴 Неделя 1: v2 использование (День 1/7)",
    "🟡 Аудит базы (Backlog, 2-4 часа)",
    "🟢 Индикатор токенов (Backlog, 1-8 часов)",
    "🟢 Confidence Scoring (Backlog, 3-4 часа)"
  ],
  "Reports": [
    "reports/DEEP_ANALYSIS_GUIDE.md",
    "reports/ERROR_LEARNING_GUIDE.md",
    "reports/ERROR_METRICS_DASHBOARD.md",
    "reports/KB_TESTING_GUIDE.md",
    "reports/TEST_REPORT.md",
    "reports/SESSION_SAVE_GUIDE.md"
  ],
  "SessionSummary": {
    "Duration": "~6 часов",
    "KeyDiscovery": "BASE_INDEX.md работает как единая точка входа",
    "TestsCreated": "10 тестов",
    "TestsPassRate": "100%",
    "DocumentationCreated": "627 строк (BASE_INDEX.md v1.4)",
    "CommitsMade": "5+",
    "FilesModified": "000-BASE_INDEX.md"
  }
}
